<?xml version="1.0" encoding="windows-1250"?>

<string_table>
	<string id="st_wpn_benelli_m1014">
		<text>Benelli M1014</text>
	</string>
	<string id="st_wpn_benelli_m1014_descr">
		<text>Benelli M4 to pó³automatyczna strzelba produkowana przez w³oskiego producenta broni palnej Benelli Armi SpA, a tak¿e czwarty i ostatni model z linii pó³automatycznych strzelb Benelli Super 90. M4 wykorzystuje opatentowany system dzia³ania zwany „automatycznie regulowanym systemem gazowym” (ARGO), który zosta³ stworzony specjalnie dla tej broni. Zaprojektowany w 1998 roku, M4 zosta³ przyjêty miêdzy innymi przez si³y zbrojne W³och, Stanów Zjednoczonych i Wielkiej Brytanii i by³ u¿ywany w ró¿nych konfliktach.\n \n
		%c[ui_gray_2]PASUJ¥CE AKCESORIA: \n
		%c[d_purple] • %c[ui_gray_2] Celowniki : OKP-2, EOt 2, EOt, AC10632, C-more, EKP8-18, RMR, Deltapoint, AIM Low, D0cter\n 
		%c[d_purple] • %c[ui_gray_2] T³umik: SALVO12 \n</text>
	</string>	
</string_table>
